ozapi/__init__.py
ozapi-0.0.1.dist-info/METADATA
ozapi-0.0.1.dist-info/WHEEL
ozapi-0.0.1.dist-info/entry_points.txt
ozapi-0.0.1.dist-info/RECORD
